{     "version": "v0.1.344",     "homepage": "https://lang.pivotstudio.cn",     "license": "MIT",     "description": "Pivot Lang Compiler and language server",     "bin": [         "plc.exe"     ],     "architecture": {         "64bit":         {             "url": "https://github.com/Pivot-Studio/pivot-lang/releases/download/v0.1.344/pivot-lang-0.1.344-windows-amd64.tar.gz",             "type": "tar.xz",             "sha256": "af18c2a5a5282f17c826f84cba56ad16aced641de215eb543a38084e22259f9d"         }     },     "env_add_path": [         "$dir"     ],     "post_install": [         "tar xvf pivot-lang-0.1.344-windows-amd64.tar.gz",         "setx KAGARI_LIB_ROOT \"$dir\\win64\\planglib\"",         "setx PL_ROOT \"$dir\\win64\""     ] }
